jdb2/__init__.py
jdb2/jdb.py
jdb2-0.2.2.dist-info/METADATA
jdb2-0.2.2.dist-info/RECORD
jdb2-0.2.2.dist-info/WHEEL
jdb2-0.2.2.dist-info/top_level.txt
jdb2-0.2.2.dist-info/zip-safe
